fabric_am/__init__.py
fabric_am/config/al2s_handler_config.yml
fabric_am/config/net_handler_config.yml
fabric_am/config/switch_handler_config.yml
fabric_am/config/vm_handler_config.yml
fabric_am/config/vnic_net_handler_config.yml
fabric_am/handlers/__init__.py
fabric_am/handlers/al2s_handler.py
fabric_am/handlers/net_handler.py
fabric_am/handlers/oess_handler.py
fabric_am/handlers/switch_handler.py
fabric_am/handlers/vm_handler.py
fabric_am/handlers/vnic_net_handler.py
fabric_am/playbooks/README.md
fabric_am/playbooks/al2s.yml
fabric_am/playbooks/fpga_provisioning.yml
fabric_am/playbooks/head_get_worker_node_for_vm.yml
fabric_am/playbooks/head_port_provisioning.yml
fabric_am/playbooks/head_switch_provisioning.yml
fabric_am/playbooks/head_vm_post_boot_config.yml
fabric_am/playbooks/head_vm_provisioning.yml
fabric_am/playbooks/head_volume_provisioning.yml
fabric_am/playbooks/inventory_template
fabric_am/playbooks/multi_function_pci_devices.yml
fabric_am/playbooks/netam_nso_data.yml
fabric_am/playbooks/nmcli_config_nw_interface.yml
fabric_am/playbooks/nvme_cleanup.yml
fabric_am/playbooks/pci_rescan.yml
fabric_am/playbooks/sn1022_fpga_provisioning.yml
fabric_am/playbooks/ssh_keys_config.yml
fabric_am/playbooks/storage_config.yml
fabric_am/playbooks/worker_libvirt_operations.yml
fabric_am/playbooks/worker_pci_provisioning.yml
fabric_am/playbooks/roles/fpga_provisioning/tasks/main.yml
fabric_am/playbooks/roles/head_get_worker_node_for_vm/tasks/main.yml
fabric_am/playbooks/roles/head_port_provisioning/tasks/main.yml
fabric_am/playbooks/roles/head_switch_provisioning/docker-compose.yml
fabric_am/playbooks/roles/head_switch_provisioning/tasks/main.yml
fabric_am/playbooks/roles/head_vm_post_boot_config/tasks/main.yml
fabric_am/playbooks/roles/head_vm_provisioning/tasks/main.yml
fabric_am/playbooks/roles/head_volume_provisioning/tasks/main.yml
fabric_am/playbooks/roles/multi_function_pci_devices/tasks/main.yml
fabric_am/playbooks/roles/nmcli_config_nw_interface/tasks/main.yml
fabric_am_handlers-1.9.1.dist-info/licenses/LICENSE
fabric_am_handlers-1.9.1.dist-info/WHEEL
fabric_am_handlers-1.9.1.dist-info/METADATA
fabric_am_handlers-1.9.1.dist-info/RECORD
