Metadata-Version: 2.4
Name: fabric_am_handlers
Version: 1.9.1
Summary: Fabric Aggregate Manager Handlers
Keywords: Fabric Control Framework,Aggregate Manager Handlers
Author-email: Komal Thareja <kthare10@renci.org>
Requires-Python: >=3.9
Classifier: Programming Language :: Python :: 3
Classifier: License :: OSI Approved :: MIT License
Classifier: Operating System :: OS Independent
License-File: LICENSE
Requires-Dist: ansible==7.5.0
Requires-Dist: paramiko
Requires-Dist: fabric-cf==1.9.1
Requires-Dist: pytest ; extra == "test"
Project-URL: Home, https://fabric-testbed.net/
Project-URL: Sources, https://github.com/fabric-testbed/ControlFramework
Provides-Extra: test
